tmt/__init__.py
tmt/imgcat.py
tmt/terminalmedia.py
tmt/utils.py
tmt/videocat.py
TerminalMedia-0.1.3.dist-info/METADATA
TerminalMedia-0.1.3.dist-info/WHEEL
TerminalMedia-0.1.3.dist-info/entry_points.txt
TerminalMedia-0.1.3.dist-info/top_level.txt
TerminalMedia-0.1.3.dist-info/RECORD
